intents_classifier_beta4/__init__.py
intents_classifier_beta4/module.py
intents_classifier_beta4-0.3.dist-info/METADATA
intents_classifier_beta4-0.3.dist-info/WHEEL
intents_classifier_beta4-0.3.dist-info/top_level.txt
intents_classifier_beta4-0.3.dist-info/RECORD
