Metadata-Version: 2.1
Name: intents-classifier-beta4
Version: 0.3
Summary: package for classifiying users requests
Home-page: http://github.com/theKirill/GensimSample
Author: Kirill Yanyushkin, Ekaterina Zababurina
Author-email: ea.zababurina@gmail.com, k.a.yanushkin@gmail.com
License: MIT
Keywords: intents,intent,classifier of intents,requests classifier
Platform: UNKNOWN
Classifier: Development Status :: 3 - Alpha
Classifier: License :: OSI Approved :: MIT License
Classifier: Programming Language :: Python :: 2.7
Classifier: Topic :: Text Processing :: Linguistic
Requires-Dist: pymorphy2
Requires-Dist: nltk
Requires-Dist: gensim
Requires-Dist: keras
Requires-Dist: sklearn
Requires-Dist: numpy
